LICENSE
MANIFEST.in
README.rst
setup.py
structured/__init__.py
structured/analyzer.py
structured/filters.py
structured/finder.py
structured/test_datasamples.py
structured/test_structured.py
structured.egg-info/PKG-INFO
structured.egg-info/SOURCES.txt
structured.egg-info/dependency_links.txt
structured.egg-info/requires.txt
structured.egg-info/top_level.txt