Metadata-Version: 1.1
Name: structured
Version: 0.1
Summary: Query Lang to extract data from structures
Home-page: https://github.com/joymax/
Author: Maksym Klymyshyn
Author-email: klymyshyn@gmail.com
License: UNKNOWN
Platform: UNKNOWN
Classifier: Development Status :: 4 - Beta
Classifier: Intended Audience :: Developers
Classifier: Operating System :: OS Independent
Classifier: Programming Language :: Python
Classifier: Programming Language :: Python :: 2.7
